som_cm/__init__.py
som_cm/som_gray_sclae.py
som_cm/core/__init__.py
som_cm/core/color_pixels.py
som_cm/core/hist_3d.py
som_cm/core/hist_common.py
som_cm/core/som.py
som_cm/cv/__init__.py
som_cm/cv/image.py
som_cm/datasets/__init__.py
som_cm/io_util/__init__.py
som_cm/io_util/image.py
som_cm/np/__init__.py
som_cm/np/norm.py
som_cm/results/__init__.py
SOMGraySclae-1.0.1.dist-info/LICENSE
SOMGraySclae-1.0.1.dist-info/METADATA
SOMGraySclae-1.0.1.dist-info/WHEEL
SOMGraySclae-1.0.1.dist-info/top_level.txt
SOMGraySclae-1.0.1.dist-info/RECORD
